__init__.py
main.py
parsers/__init__.py
parsers/common/__init__.py
parsers/common/cellparser.py
parsers/common/rowdatasheet.py
parsers/common/rowparser.py
parsers/common/sheetparser.py
parsers/creation/__init__.py
parsers/creation/constants.py
parsers/creation/contentindexparser.py
parsers/creation/contentindexrowmodel.py
parsers/creation/datarowmodel.py
parsers/creation/flowparser.py
parsers/creation/flowrowmodel.py
parsers/creation/template_sheet_parser.py
parsers/sheets/__init__.py
parsers/sheets/csv_sheet_reader.py
parsers/sheets/google_sheet_reader.py
parsers/sheets/xlsx_sheet_reader.py
rapidpro/__init__.py
rapidpro/utils.py
rapidpro/models/actions.py
rapidpro/models/common.py
rapidpro/models/containers.py
rapidpro/models/nodes.py
rapidpro/models/routers.py
rapidpro_flow_toolkit-0.0.1.dist-info/METADATA
rapidpro_flow_toolkit-0.0.1.dist-info/WHEEL
rapidpro_flow_toolkit-0.0.1.dist-info/licenses/LICENSE
rapidpro_flow_toolkit-0.0.1.dist-info/RECORD
