Metadata-Version: 2.1
Name: rapidpro_flow_toolkit
Version: 0.0.1
Summary: Toolkit for using spreadsheets to create and modify RapidPro flows
Project-URL: Homepage, https://github.com/IDEMSInternational/rapidpro-flow-toolkit
Project-URL: Bug Tracker, https://github.com/IDEMSInternational/rapidpro-flow-toolkit/issues
Author-email: Ed Moss <ed.moss@eemengineering.com>
License-File: LICENSE
Classifier: License :: OSI Approved :: MIT License
Classifier: Operating System :: OS Independent
Classifier: Programming Language :: Python :: 3
Requires-Python: >=3.7
